data_transfer_lib/__init__.py
data_transfer_lib/connections/__init__.py
data_transfer_lib/connections/base.py
data_transfer_lib/connections/clickhouse.py
data_transfer_lib/connections/postgres.py
data_transfer_lib/reader/__init__.py
data_transfer_lib/reader/base.py
data_transfer_lib/reader/reader.py
data_transfer_lib/schema/__init__.py
data_transfer_lib/schema/mapper.py
data_transfer_lib/schema/validator.py
data_transfer_lib/utils/__init__.py
data_transfer_lib/utils/exceptions.py
data_transfer_lib/writer/__init__.py
data_transfer_lib/writer/base.py
data_transfer_lib/writer/writer.py
data_transfer_lib-0.1.3.dist-info/METADATA
data_transfer_lib-0.1.3.dist-info/WHEEL
data_transfer_lib-0.1.3.dist-info/top_level.txt
data_transfer_lib-0.1.3.dist-info/RECORD
